iossecuworm/__init__.py
iossecuworm/__main__.py
iossecuworm-0.0.6.dist-info/LICENSE
iossecuworm-0.0.6.dist-info/METADATA
iossecuworm-0.0.6.dist-info/WHEEL
iossecuworm-0.0.6.dist-info/entry_points.txt
iossecuworm-0.0.6.dist-info/top_level.txt
iossecuworm-0.0.6.dist-info/RECORD
