Metadata-Version: 2.1
Name: iossecuworm
Version: 0.0.6
Summary: secuworm's iOS
Home-page: https://github.com/secuworm/iossecuworm
Author: secuworm
Author-email: secuworm@naver.com
License: UNKNOWN
Platform: UNKNOWN
Classifier: Programming Language :: Python :: 3
Classifier: License :: OSI Approved :: MIT License
Classifier: Operating System :: OS Independent
